jitcc-0.0.1.dist-info/WHEEL
jitcc-0.0.1.dist-info/entry_points.txt
jitcc-0.0.1.dist-info/LICENSE
jitcc-0.0.1.dist-info/top_level.txt
jitcc-0.0.1.dist-info/RECORD
jitcc-0.0.1.dist-info/METADATA
jitcc/core.cpython-310-x86_64-linux-gnu.so
jitcc/libjitcc.so
jitcc/libtcc.so
jitcc/pkginfo.py
jitcc/__init__.py
jitcc/share/include/jit/cc/IFactory.h
jitcc/share/include/jit/cc/IJitCC.h
jitcc/share/include/jit/cc/FactoryExt.h
